examples/telmbot-ctrl-win/telmbot-ctrl-win.py
pytelmbot/__init__.py
pytelmbot/sdwire.py
pytelmbot-0.1.3.dist-info/licenses/LICENSE
pytelmbot-0.1.3.dist-info/METADATA
pytelmbot-0.1.3.dist-info/WHEEL
pytelmbot-0.1.3.dist-info/top_level.txt
pytelmbot-0.1.3.dist-info/RECORD
