Metadata-Version: 2.4
Name: pytelmbot
Version: 0.1.3
Summary: A collection of utilities to use for automated embedded testing
Author-email: "Telmtron Ltd." <create@telmtron.tech>
License: MIT
Project-URL: Homepage, https://github.com/Telmtron-Ltd/pytelmbot
Classifier: Programming Language :: Python :: 3
Classifier: License :: OSI Approved :: MIT License
Classifier: Operating System :: OS Independent
Requires-Python: >=3.7
License-File: LICENSE
Requires-Dist: ftd2xx>=1.3.8
Requires-Dist: psutil>=7.0.0
Provides-Extra: examples
Requires-Dist: wxpython; extra == "examples"
Dynamic: license-file
